{
	"name": "Raincatching",
	"type": "improvement",
	"flags": {},
	"_id": "OoDfv0tH2yTLWez0",
	"_key": "!items!OoDfv0tH2yTLWez0",
	"system": {
		"slug": "raincatching",
		"sortOrder": 12,
		"choices": {
			"slug": "raincatching",
			"list": [
				{
					"type": "heading",
					"content": {
						"title": "Raincatching",
						"text": "<p>Filling the cistern takes so much work. Surely, we can do better!</p>"
					}
				},
				{
					"type": "heading",
					"content": {
						"title": null,
						"text": "<p><strong>Requires</strong> all of the following, in order:</p>"
					}
				},
				{
					"type": "heading",
					"slug": "engineer-foreman",
					"content": {
						"title": null,
						"text": "An <em>exceptional</em> engineer/foreman, to design a cunning system of roofs, gutters, and conduits"
					},
					"track": {
						"max": 1
					}
				},
				{
					"type": "heading",
					"slug": "slate-terracotta",
					"content": {
						"title": null,
						"text": "Enough slate/terracotta to roof all the buildings and construct the gutters and conduits (Value 3)"
					},
					"track": {
						"max": 1
					}
				},
				{
					"type": "heading",
					"slug": "pull-together",
					"content": {
						"title": null,
						"text": "Pulling Together 3 times, each requiring 1 season and 1 Surplus"
					},
					"track": {
						"max": 3
					}
				},
				{
					"type": "heading",
					"content": {
						"title": null,
						"text": "<p>When you <strong><em>meet the requirements</em></strong>, increase Fortunes by 1, add \"Raincatching\" to the Resources list.</p><p>Henceforth, when summer comes and you roll a 7+ with Fortunes, the steading generates 1 Surplus.</p>"
					}
				}
			]
		}
	}
}
